{
  "children": [
    {
      "type": "书名",
      "lines": [
        {
          "type": "句",
          "value": "《彖》曰：大觀在上，",
          "children": [
            {
              "type": "释文",
              "text": "大觀，王肅音官。 "
            }
          ]
        },
        {
          "type": "句",
          "value": "順而巽，中正以觀天下。",
          "children": [
            {
              "type": "释文",
              "text": "以觀，徐唯此一字作官音。 "
            }
          ]
        },
        {
          "type": "句",
          "value": "觀，盥而不薦，有孚顒若，下觀而化也。"
        },
        {
          "type": "句",
          "value": "觀天之神道，而四時不忒。",
          "children": [
            {
              "type": "集解",
              "list": [
                {
                  "text": "大傳曰：誣神者殃及三世。",
                  "book": "［漢書］"
                }
              ]
            }
          ]
        },
        {
          "type": "句",
          "value": "聖人以神道設教，而天下服矣。",
          "children": [
            {
              "type": "释文",
              "text": "神道設教，一本作以神道設教。 "
            }
          ]
        },
        {
          "type": "句",
          "value": "《象》曰：風行地上，觀。先王以省方觀民設教。",
          "children": [
            {
              "type": "集解",
              "list": [
                {
                  "text": "鄭眾曰：從俗所為順民之教，故君子治人不求變俗。",
                  "book": "［口訣義］"
                }
              ]
            }
          ]
        },
        {
          "type": "句",
          "value": "初六，童觀，小人无咎，君子吝。",
          "children": [
            {
              "type": "集解",
              "list": [
                {
                  "text": "馬融曰：童猶獨也。",
                  "book": "［釋文］"
                },
                {
                  "text": "　鄭康成曰：童稚也。",
                  "book": "［同］"
                }
              ]
            }
          ]
        },
        {
          "type": "句",
          "value": "《象》曰：初六童觀，小人道也。"
        },
        {
          "type": "句",
          "value": "六二，闚觀，利女貞。",
          "children": [
            {
              "type": "释文",
              "text": "闚，本又作窺。 "
            }
          ]
        },
        {
          "type": "句",
          "value": "《象》曰：闚觀女貞，亦可醜也。",
          "children": [
            {
              "type": "释文",
              "text": "象曰闚觀女貞，一本有利字。 "
            }
          ]
        },
        {
          "type": "句",
          "value": "六三，觀我生，進退。"
        },
        {
          "type": "句",
          "value": "《象》曰：觀我生進退，未失道也。"
        },
        {
          "type": "句",
          "value": "六四，觀國之光，利用賓于王。",
          "children": [
            {
              "type": "释文",
              "text": "觀國之光，如字。或音官喚反。 "
            }
          ]
        },
        {
          "type": "句",
          "value": "《象》曰：觀國之光，尚賓也。"
        },
        {
          "type": "句",
          "value": "九五，觀我生，君子无咎。"
        },
        {
          "type": "句",
          "value": "《象》曰：觀我生，觀民也。"
        },
        {
          "type": "句",
          "value": "上九，觀其生，君子无咎。",
          "children": [
            {
              "type": "集解",
              "list": [
                {
                  "text": "王傳云：獨處異地，不易執持。",
                  "book": "［口訣義］"
                }
              ]
            }
          ]
        },
        {
          "type": "句",
          "value": "《象》曰：觀其生，志未平也。"
        },
        {
          "type": "句",
          "value": "　"
        }
      ]
    }
  ]
}